searXNG/__init__.py
searXNG/__main__.py
searXNG/client.py
searXNG/server.py
searxng-0.0.0.dev0.dist-info/WHEEL
searxng-0.0.0.dev0.dist-info/entry_points.txt
searxng-0.0.0.dev0.dist-info/METADATA
searxng-0.0.0.dev0.dist-info/RECORD
