Metadata-Version: 2.3
Name: searxng
Version: 0.0.0.dev0
Summary: MCP server providing SearXNG-based web search functionality
Author: D. Danchev
Author-email: D. Danchev <12420863+danchev@users.noreply.github.com>
License: AGPL-3.0-or-later
Classifier: License :: OSI Approved :: GNU Affero General Public License v3 or later (AGPLv3+)
Classifier: Development Status :: 2 - Pre-Alpha
Classifier: Operating System :: OS Independent
Classifier: Intended Audience :: Developers
Classifier: Intended Audience :: Information Technology
Classifier: Topic :: Scientific/Engineering
Classifier: Topic :: Scientific/Engineering :: Artificial Intelligence
Classifier: Topic :: Scientific/Engineering :: Interface Engine/Protocol Translator
Classifier: Topic :: Software Development :: Libraries
Classifier: Topic :: Software Development :: Libraries :: Python Modules
Classifier: Programming Language :: Python
Classifier: Programming Language :: Python :: 3
Classifier: Programming Language :: Python :: 3.11
Classifier: Programming Language :: Python :: 3.12
Classifier: Programming Language :: Python :: 3.13
Classifier: Programming Language :: Python :: 3.14
Classifier: Programming Language :: Python :: 3 :: Only
Requires-Dist: mcp[cli]>=1.14.0
Requires-Dist: requests>=2.32.5
Requires-Python: >=3.11
Project-URL: Documentation, https://danchev.github.io/searXNG/
Project-URL: Issues, https://github.com/danchev/searXNG/issues
Project-URL: Source, https://github.com/danchev/searXNG
